jsonschema_default/__init__.py
jsonschema_default/errors.py
jsonschema_default/main.py
jsonschema_default-1.8.0.dist-info/METADATA
jsonschema_default-1.8.0.dist-info/WHEEL
jsonschema_default-1.8.0.dist-info/licenses/LICENSE
jsonschema_default-1.8.0.dist-info/RECORD
