Metadata-Version: 2.4
Name: jsonschema-default
Version: 1.8.0
Summary: Create default objects from a JSON schema
Project-URL: homepage, https://github.com/mnboos/jsonschema-default
Project-URL: repository, https://github.com/mnboos/jsonschema-default
Author-email: Martin Boos <mboos@outlook.com>
Maintainer-email: Martin Boos <mboos@outlook.com>
License: GNU AGPL v3
License-File: LICENSE
Requires-Python: <4.0,>=3.9
Requires-Dist: rstr==3.2.2
